casbin_peewee_adapter/__init__.py
casbin_peewee_adapter/adapter.py
casbin_peewee_adapter/config.py
casbin_peewee_adapter-0.0.2.data/data/README.md
casbin_peewee_adapter-0.0.2.dist-info/LICENSE
casbin_peewee_adapter-0.0.2.dist-info/METADATA
casbin_peewee_adapter-0.0.2.dist-info/WHEEL
casbin_peewee_adapter-0.0.2.dist-info/top_level.txt
casbin_peewee_adapter-0.0.2.dist-info/RECORD
