Metadata-Version: 2.1
Name: casbin-peewee-adapter
Version: 0.0.2
Summary: Peewee Adapter for PyCasbin
Home-page: https://github.com/shblhy/peewee-adapter
Author: Huang Yan
Author-email: hyor@foxmail.com
License: Apache 2.0
Keywords: casbin,Peewee,casbin-adapter,rbac,access control,abac,acl,permission
Platform: UNKNOWN
Classifier: Programming Language :: Python :: 3.3
Classifier: Programming Language :: Python :: 3.4
Classifier: Programming Language :: Python :: 3.5
Classifier: Programming Language :: Python :: 3.6
Classifier: Programming Language :: Python :: 3.7
Classifier: License :: OSI Approved :: Apache Software License
Classifier: Operating System :: OS Independent
Requires-Python: >=3.3
Requires-Dist: casbin (>=0.2)
Requires-Dist: peewee (>=3.1.0)
